{
    "dept": [
        {
            "name": "研发部",
            "dept": [
                {
                    "name": "研发1部",
                    "dept": [
                        {
                            "name": "研发1组"
                        },
                        {
                            "name": "研发2组"
                        }
                    ]
                },
                {
                    "name": "研发2部",
                    "dept": [
                        {
                            "name": "研发1组"
                        },
                        {
                            "name": "研发2组"
                        }
                    ]
                }
            ]
        },
        {
            "name": "运营部",
            "dept": [
                {
                    "name": "运营1部",
                    "dept": [
                        {
                            "name": "运营1组"
                        },
                        {
                            "name": "运营2组"
                        }
                    ]
                },
                {
                    "name": "运营2部",
                    "dept": [
                        {
                            "name": "运营1组"
                        },
                        {
                            "name": "运营2组"
                        }
                    ]
                }
            ]
        }
    ]
}